simple_ranker
