Metadata-Version: 1.1
Name: simple-ranker
Version: 1.0.1
Summary: An extremely simple, multi-value ranking module for pandas DataFrames
Home-page: https://github.com/lextoumbourou/simple-ranker
Author: Lex Toumbourou
Author-email: lextoumbourou@gmail.com
License: MIT
Platform: UNKNOWN
Classifier: Intended Audience :: Developers
Classifier: Topic :: Utilities
Classifier: Programming Language :: Python
